Proyecto 3/binary_to_bcd.sv
//==================================================
// archivo: binary_to_bcd.sv
// Descripcion: Conversion de numero binario a representacion BCD
// mediante el algoritmo "double-dabble" (shift-and-add-3).
//
// El algoritmo funciona de la siguiente forma:
//   1. Se desplaza el numero binario bit a bit hacia el registro BCD.
//   2. Antes de cada desplazamiento, si algun digito BCD es >= 5,
//      se le suman 3 (para corregir el desbordamiento BCD).
//   3. Se repite INPUT_WIDTH veces.
//
// Esta es una implementacion combinacional (unrolled), apropiada para
// FPGA con anchos de datos pequeños como los de este proyecto.
//
// Parametros:
//   INPUT_WIDTH  : ancho del numero binario (6 para cociente, 4 para residuo)
//   BCD_DIGITS   : numero de digitos BCD requeridos
//     max(63)  -> 2 digitos BCD
//     max(127) -> 3 digitos BCD
//
// Proyecto: EL-3307 Diseño Logico I-2026
//==================================================

module binary_to_bcd #(
    parameter INPUT_WIDTH = 6,
    parameter BCD_DIGITS  = 2   // numero de digitos decimales de salida
)(
    input  logic [INPUT_WIDTH-1:0]    bin_i,
    output logic [BCD_DIGITS*4-1:0]  bcd_o
);

    // ------- Implementacion double-dabble combinacional -------
    // Se crean INPUT_WIDTH niveles de corrección
    // Cada nivel tiene BCD_DIGITS digitos de 4 bits + el binario restante

    // Array de trabajo: [nivel][BCD_DIGITS digitos + bits del binario]
    // Dimension total por nivel: BCD_DIGITS*4 + INPUT_WIDTH bits
    localparam TOTAL_BITS = BCD_DIGITS * 4 + INPUT_WIDTH;

    logic [TOTAL_BITS-1:0] work [INPUT_WIDTH:0];

    // Inicializar: el binario en los bits bajos, BCD en cero
    always_comb begin : double_dabble
        integer lvl, d;

        // Nivel inicial: BCD=0, binario=bin_i
        work[0] = {{(BCD_DIGITS*4){1'b0}}, bin_i};

        for (lvl = 0; lvl < INPUT_WIDTH; lvl++) begin
            // Paso 1: Correccion (add-3 si digito >= 5)
            work[lvl+1] = work[lvl];
            for (d = 0; d < BCD_DIGITS; d++) begin
                // Indice del digito en work: bits [INPUT_WIDTH + d*4 + 3 : INPUT_WIDTH + d*4]
                if (work[lvl+1][INPUT_WIDTH + d*4 +: 4] >= 4'd5)
                    work[lvl+1][INPUT_WIDTH + d*4 +: 4] =
                        work[lvl+1][INPUT_WIDTH + d*4 +: 4] + 4'd3;
            end
            // Paso 2: Desplazamiento a la izquierda (shift left 1)
            work[lvl+1] = work[lvl+1] << 1;
        end

        // Extraer digitos BCD del resultado final
        bcd_o = work[INPUT_WIDTH][TOTAL_BITS-1 : INPUT_WIDTH];
    end

endmodule

Proyecto 3/proyecto_division/tb/tb_binary_to_bcd.sv
//==================================================
// archivo: tb_binary_to_bcd.sv
// Descripcion: Testbench para binary_to_bcd (double-dabble).
// Verifica la conversion correcta para todos los rangos relevantes
// del proyecto: 0-63 (base) y 0-127 (extra).
// Proyecto: EL-3307 Diseño Logico I-2026
//==================================================

`timescale 1ns/1ps

module tb_binary_to_bcd;

    // ---- Version base: 6 bits, 2 digitos ----
    logic [5:0] bin6;
    logic [7:0] bcd8;   // 2 digitos x 4 bits

    binary_to_bcd #(.INPUT_WIDTH(6), .BCD_DIGITS(2)) dut_base (
        .bin_i(bin6),
        .bcd_o(bcd8)
    );

    // ---- Version extra: 7 bits, 3 digitos ----
    logic [6:0]  bin7;
    logic [11:0] bcd12;  // 3 digitos x 4 bits

    binary_to_bcd #(.INPUT_WIDTH(7), .BCD_DIGITS(3)) dut_extra (
        .bin_i(bin7),
        .bcd_o(bcd12)
    );

    // Funcion de referencia: bin -> digitos decimales
    function automatic logic [7:0] ref_bcd2(input integer val);
        return {4'(val / 10), 4'(val % 10)};
    endfunction

    function automatic logic [11:0] ref_bcd3(input integer val);
        return {4'(val / 100), 4'((val / 10) % 10), 4'(val % 10)};
    endfunction

    integer i;
    integer pass_cnt, fail_cnt;

    initial begin
        $dumpfile("tb_binary_to_bcd.vcd");
        $dumpvars(0, tb_binary_to_bcd);

        pass_cnt = 0;
        fail_cnt = 0;

        $display("=== Test binary_to_bcd version base (6 bits, 2 digitos) ===");
        for (i = 0; i <= 63; i++) begin
            bin6 = i[5:0];
            #10;
            if (bcd8 == ref_bcd2(i)) begin
                pass_cnt++;
            end else begin
                $error("FAIL: bin=%0d => bcd=%h (esperado %h)",
                    i, bcd8, ref_bcd2(i));
                fail_cnt++;
            end
        end
        $display("  Base: %0d PASS, %0d FAIL", pass_cnt, fail_cnt);

        pass_cnt = 0; fail_cnt = 0;

        $display("=== Test binary_to_bcd version extra (7 bits, 3 digitos) ===");
        for (i = 0; i <= 127; i++) begin
            bin7 = i[6:0];
            #10;
            if (bcd12 == ref_bcd3(i)) begin
                pass_cnt++;
            end else begin
                $error("FAIL: bin=%0d => bcd=%h (esperado %h)",
                    i, bcd12, ref_bcd3(i));
                fail_cnt++;
            end
        end
        $display("  Extra: %0d PASS, %0d FAIL", pass_cnt, fail_cnt);

        $display("=== Testbench BCD completado ===");
        $finish;
    end

endmodule

Proyecto 3/proyecto_division/tb_binary_to_bcd.vcd
$date
	Sat May 30 19:42:41 2026
$end
$version
	Icarus Verilog
$end
$timescale
	1ps
$end
$scope module tb_binary_to_bcd $end
$var wire 8 ! bcd8 [7:0] $end
$var wire 12 " bcd12 [11:0] $end
$var reg 6 # bin6 [5:0] $end
$var reg 7 $ bin7 [6:0] $end
$var integer 32 % fail_cnt [31:0] $end
$var integer 32 & i [31:0] $end
$var integer 32 ' pass_cnt [31:0] $end
$scope function ref_bcd2 $end
$upscope $end
$scope function ref_bcd3 $end
$upscope $end
$scope module dut_base $end
$var wire 6 ( bin_i [5:0] $end
$var parameter 32 ) BCD_DIGITS $end
$var parameter 32 * INPUT_WIDTH $end
$var parameter 65 + TOTAL_BITS $end
$var reg 8 , bcd_o [7:0] $end
$scope begin double_dabble $end
$var integer 32 - d [31:0] $end
$var integer 32 . lvl [31:0] $end
$upscope $end
$upscope $end
$scope module dut_extra $end
$var wire 7 / bin_i [6:0] $end
$var parameter 32 0 BCD_DIGITS $end
$var parameter 32 1 INPUT_WIDTH $end
$var parameter 65 2 TOTAL_BITS $end
$var reg 12 3 bcd_o [11:0] $end
$scope begin double_dabble $end
$var integer 32 4 d [31:0] $end
$var integer 32 5 lvl [31:0] $end
$upscope $end
$upscope $end
$upscope $end
$enddefinitions $end
$comment Show the parameter values. $end
$dumpall
b10011 2
b111 1
b11 0
b1110 +
b110 *
b10 )
$end
#0
$dumpvars
b111 5
b11 4
b0xxxxxxx 3
bx /
b110 .
b10 -
b0 ,
b0 (
b0 '
b0 &
b0 %
bx $
b0 #
b0xxxxxxx "
b0 !
$end
#10000
b1 !
b1 ,
b10 -
b110 .
b1 #
b1 (
b1 &
b1 '
#20000
b10 !
b10 ,
b10 -
b110 .
b10 #
b10 (
b10 &
b10 '
#30000
b11 !
b11 ,
b10 -
b110 .
b11 #
b11 (
b11 &
b11 '
#40000
b100 !
b100 ,
b10 -
b110 .
b100 #
b100 (
b100 &
b100 '
#50000
b101 !
b101 ,
b10 -
b110 .
b101 #
b101 (
b101 &
b101 '
#60000
b110 !
b110 ,
b10 -
b110 .
b110 #
b110 (
b110 &
b110 '
#70000
b111 !
b111 ,
b10 -
b110 .
b111 #
b111 (
b111 &
b111 '
#80000
b1000 !
b1000 ,
b10 -
b110 .
b1000 #
b1000 (
b1000 &
b1000 '
#90000
b1001 !
b1001 ,
b10 -
b110 .
b1001 #
b1001 (
b1001 &
b1001 '
#100000
b10000 !
b10000 ,
b10 -
b110 .
b1010 #
b1010 (
b1010 &
b1010 '
#110000
b10001 !
b10001 ,
b10 -
b110 .
b1011 #
b1011 (
b1011 &
b1011 '
#120000
b10010 !
b10010 ,
b10 -
b110 .
b1100 #
b1100 (
b1100 &
b1100 '
#130000
b10011 !
b10011 ,
b10 -
b110 .
b1101 #
b1101 (
b1101 &
b1101 '
#140000
b10100 !
b10100 ,
b10 -
b110 .
b1110 #
b1110 (
b1110 &
b1110 '
#150000
b10101 !
b10101 ,
b10 -
b110 .
b1111 #
b1111 (
b1111 &
b1111 '
#160000
b10110 !
b10110 ,
b10 -
b110 .
b10000 #
b10000 (
b10000 &
b10000 '
#170000
b10111 !
b10111 ,
b10 -
b110 .
b10001 #
b10001 (
b10001 &
b10001 '
#180000
b11000 !
b11000 ,
b10 -
b110 .
b10010 #
b10010 (
b10010 &
b10010 '
#190000
b11001 !
b11001 ,
b10 -
b110 .
b10011 #
b10011 (
b10011 &
b10011 '
#200000
b100000 !
b100000 ,
b10 -
b110 .
b10100 #
b10100 (
b10100 &
b10100 '
#210000
b100001 !
b100001 ,
b10 -
b110 .
b10101 #
b10101 (
b10101 &
b10101 '
#220000
b100010 !
b100010 ,
b10 -
b110 .
b10110 #
b10110 (
b10110 &
b10110 '
#230000
b100011 !
b100011 ,
b10 -
b110 .
b10111 #
b10111 (
b10111 &
b10111 '
#240000
b100100 !
b100100 ,
b10 -
b110 .
b11000 #
b11000 (
b11000 &
b11000 '
#250000
b100101 !
b100101 ,
b10 -
b110 .
b11001 #
b11001 (
b11001 &
b11001 '
#260000
b100110 !
b100110 ,
b10 -
b110 .
b11010 #
b11010 (
b11010 &
b11010 '
#270000
b100111 !
b100111 ,
b10 -
b110 .
b11011 #
b11011 (
b11011 &
b11011 '
#280000
b101000 !
b101000 ,
b10 -
b110 .
b11100 #
b11100 (
b11100 &
b11100 '
#290000
b101001 !
b101001 ,
b10 -
b110 .
b11101 #
b11101 (
b11101 &
b11101 '
#300000
b110000 !
b110000 ,
b10 -
b110 .
b11110 #
b11110 (
b11110 &
b11110 '
#310000
b110001 !
b110001 ,
b10 -
b110 .
b11111 #
b11111 (
b11111 &
b11111 '
#320000
b110010 !
b110010 ,
b10 -
b110 .
b100000 #
b100000 (
b100000 &
b100000 '
#330000
b110011 !
b110011 ,
b10 -
b110 .
b100001 #
b100001 (
b100001 &
b100001 '
#340000
b110100 !
b110100 ,
b10 -
b110 .
b100010 #
b100010 (
b100010 &
b100010 '
#350000
b110101 !
b110101 ,
b10 -
b110 .
b100011 #
b100011 (
b100011 &
b100011 '
#360000
b110110 !
b110110 ,
b10 -
b110 .
b100100 #
b100100 (
b100100 &
b100100 '
#370000
b110111 !
b110111 ,
b10 -
b110 .
b100101 #
b100101 (
b100101 &
b100101 '
#380000
b111000 !
b111000 ,
b10 -
b110 .
b100110 #
b100110 (
b100110 &
b100110 '
#390000
b111001 !
b111001 ,
b10 -
b110 .
b100111 #
b100111 (
b100111 &
b100111 '
#400000
b1000000 !
b1000000 ,
b10 -
b110 .
b101000 #
b101000 (
b101000 &
b101000 '
#410000
b1000001 !
b1000001 ,
b10 -
b110 .
b101001 #
b101001 (
b101001 &
b101001 '
#420000
b1000010 !
b1000010 ,
b10 -
b110 .
b101010 #
b101010 (
b101010 &
b101010 '
#430000
b1000011 !
b1000011 ,
b10 -
b110 .
b101011 #
b101011 (
b101011 &
b101011 '
#440000
b1000100 !
b1000100 ,
b10 -
b110 .
b101100 #
b101100 (
b101100 &
b101100 '
#450000
b1000101 !
b1000101 ,
b10 -
b110 .
b101101 #
b101101 (
b101101 &
b101101 '
#460000
b1000110 !
b1000110 ,
b10 -
b110 .
b101110 #
b101110 (
b101110 &
b101110 '
#470000
b1000111 !
b1000111 ,
b10 -
b110 .
b101111 #
b101111 (
b101111 &
b101111 '
#480000
b1001000 !
b1001000 ,
b10 -
b110 .
b110000 #
b110000 (
b110000 &
b110000 '
#490000
b1001001 !
b1001001 ,
b10 -
b110 .
b110001 #
b110001 (
b110001 &
b110001 '
#500000
b1010000 !
b1010000 ,
b10 -
b110 .
b110010 #
b110010 (
b110010 &
b110010 '
#510000
b1010001 !
b1010001 ,
b10 -
b110 .
b110011 #
b110011 (
b110011 &
b110011 '
#520000
b1010010 !
b1010010 ,
b10 -
b110 .
b110100 #
b110100 (
b110100 &
b110100 '
#530000
b1010011 !
b1010011 ,
b10 -
b110 .
b110101 #
b110101 (
b110101 &
b110101 '
#540000
b1010100 !
b1010100 ,
b10 -
b110 .
b110110 #
b110110 (
b110110 &
b110110 '
#550000
b1010101 !
b1010101 ,
b10 -
b110 .
b110111 #
b110111 (
b110111 &
b110111 '
#560000
b1010110 !
b1010110 ,
b10 -
b110 .
b111000 #
b111000 (
b111000 &
b111000 '
#570000
b1010111 !
b1010111 ,
b10 -
b110 .
b111001 #
b111001 (
b111001 &
b111001 '
#580000
b1011000 !
b1011000 ,
b10 -
b110 .
b111010 #
b111010 (
b111010 &
b111010 '
#590000
b1011001 !
b1011001 ,
b10 -
b110 .
b111011 #
b111011 (
b111011 &
b111011 '
#600000
b1100000 !
b1100000 ,
b10 -
b110 .
b111100 #
b111100 (
b111100 &
b111100 '
#610000
b1100001 !
b1100001 ,
b10 -
b110 .
b111101 #
b111101 (
b111101 &
b111101 '
#620000
b1100010 !
b1100010 ,
b10 -
b110 .
b111110 #
b111110 (
b111110 &
b111110 '
#630000
b1100011 !
b1100011 ,
b10 -
b110 .
b111111 #
b111111 (
b111111 &
b111111 '
#640000
b0 "
b0 3
b11 4
b111 5
b0 $
b0 /
b0 &
b0 '
#650000
b1 "
b1 3
b11 4
b111 5
b1 $
b1 /
b1 &
b1 '
#660000
b10 "
b10 3
b11 4
b111 5
b10 $
b10 /
b10 &
b10 '
#670000
b11 "
b11 3
b11 4
b111 5
b11 $
b11 /
b11 &
b11 '
#680000
b100 "
b100 3
b11 4
b111 5
b100 $
b100 /
b100 &
b100 '
#690000
b101 "
b101 3
b11 4
b111 5
b101 $
b101 /
b101 &
b101 '
#700000
b110 "
b110 3
b11 4
b111 5
b110 $
b110 /
b110 &
b110 '
#710000
b111 "
b111 3
b11 4
b111 5
b111 $
b111 /
b111 &
b111 '
#720000
b1000 "
b1000 3
b11 4
b111 5
b1000 $
b1000 /
b1000 &
b1000 '
#730000
b1001 "
b1001 3
b11 4
b111 5
b1001 $
b1001 /
b1001 &
b1001 '
#740000
b10000 "
b10000 3
b11 4
b111 5
b1010 $
b1010 /
b1010 &
b1010 '
#750000
b10001 "
b10001 3
b11 4
b111 5
b1011 $
b1011 /
b1011 &
b1011 '
#760000
b10010 "
b10010 3
b11 4
b111 5
b1100 $
b1100 /
b1100 &
b1100 '
#770000
b10011 "
b10011 3
b11 4
b111 5
b1101 $
b1101 /
b1101 &
b1101 '
#780000
b10100 "
b10100 3
b11 4
b111 5
b1110 $
b1110 /
b1110 &
b1110 '
#790000
b10101 "
b10101 3
b11 4
b111 5
b1111 $
b1111 /
b1111 &
b1111 '
#800000
b10110 "
b10110 3
b11 4
b111 5
b10000 $
b10000 /
b10000 &
b10000 '
#810000
b10111 "
b10111 3
b11 4
b111 5
b10001 $
b10001 /
b10001 &
b10001 '
#820000
b11000 "
b11000 3
b11 4
b111 5
b10010 $
b10010 /
b10010 &
b10010 '
#830000
b11001 "
b11001 3
b11 4
b111 5
b10011 $
b10011 /
b10011 &
b10011 '
#840000
b100000 "
b100000 3
b11 4
b111 5
b10100 $
b10100 /
b10100 &
b10100 '
#850000
b100001 "
b100001 3
b11 4
b111 5
b10101 $
b10101 /
b10101 &
b10101 '
#860000
b100010 "
b100010 3
b11 4
b111 5
b10110 $
b10110 /
b10110 &
b10110 '
#870000
b100011 "
b100011 3
b11 4
b111 5
b10111 $
b10111 /
b10111 &
b10111 '
#880000
b100100 "
b100100 3
b11 4
b111 5
b11000 $
b11000 /
b11000 &
b11000 '
#890000
b100101 "
b100101 3
b11 4
b111 5
b11001 $
b11001 /
b11001 &
b11001 '
#900000
b100110 "
b100110 3
b11 4
b111 5
b11010 $
b11010 /
b11010 &
b11010 '
#910000
b100111 "
b100111 3
b11 4
b111 5
b11011 $
b11011 /
b11011 &
b11011 '
#920000
b101000 "
b101000 3
b11 4
b111 5
b11100 $
b11100 /
b11100 &
b11100 '
#930000
b101001 "
b101001 3
b11 4
b111 5
b11101 $
b11101 /
b11101 &
b11101 '
#940000
b110000 "
b110000 3
b11 4
b111 5
b11110 $
b11110 /
b11110 &
b11110 '
#950000
b110001 "
b110001 3
b11 4
b111 5
b11111 $
b11111 /
b11111 &
b11111 '
#960000
b110010 "
b110010 3
b11 4
b111 5
b100000 $
b100000 /
b100000 &
b100000 '
#970000
b110011 "
b110011 3
b11 4
b111 5
b100001 $
b100001 /
b100001 &
b100001 '
#980000
b110100 "
b110100 3
b11 4
b111 5
b100010 $
b100010 /
b100010 &
b100010 '
#990000
b110101 "
b110101 3
b11 4
b111 5
b100011 $
b100011 /
b100011 &
b100011 '
#1000000
b110110 "
b110110 3
b11 4
b111 5
b100100 $
b100100 /
b100100 &
b100100 '
#1010000
b110111 "
b110111 3
b11 4
b111 5
b100101 $
b100101 /
b100101 &
b100101 '
#1020000
b111000 "
b111000 3
b11 4
b111 5
b100110 $
b100110 /
b100110 &
b100110 '
#1030000
b111001 "
b111001 3
b11 4
b111 5
b100111 $
b100111 /
b100111 &
b100111 '
#1040000
b1000000 "
b1000000 3
b11 4
b111 5
b101000 $
b101000 /
b101000 &
b101000 '
#1050000
b1000001 "
b1000001 3
b11 4
b111 5
b101001 $
b101001 /
b101001 &
b101001 '
#1060000
b1000010 "
b1000010 3
b11 4
b111 5
b101010 $
b101010 /
b101010 &
b101010 '
#1070000
b1000011 "
b1000011 3
b11 4
b111 5
b101011 $
b101011 /
b101011 &
b101011 '
#1080000
b1000100 "
b1000100 3
b11 4
b111 5
b101100 $
b101100 /
b101100 &
b101100 '
#1090000
b1000101 "
b1000101 3
b11 4
b111 5
b101101 $
b101101 /
b101101 &
b101101 '
#1100000
b1000110 "
b1000110 3
b11 4
b111 5
b101110 $
b101110 /
b101110 &
b101110 '
#1110000
b1000111 "
b1000111 3
b11 4
b111 5
b101111 $
b101111 /
b101111 &
b101111 '
#1120000
b1001000 "
b1001000 3
b11 4
b111 5
b110000 $
b110000 /
b110000 &
b110000 '
#1130000
b1001001 "
b1001001 3
b11 4
b111 5
b110001 $
b110001 /
b110001 &
b110001 '
#1140000
b1010000 "
b1010000 3
b11 4
b111 5
b110010 $
b110010 /
b110010 &
b110010 '
#1150000
b1010001 "
b1010001 3
b11 4
b111 5
b110011 $
b110011 /
b110011 &
b110011 '
#1160000
b1010010 "
b1010010 3
b11 4
b111 5
b110100 $
b110100 /
b110100 &
b110100 '
#1170000
b1010011 "
b1010011 3
b11 4
b111 5
b110101 $
b110101 /
b110101 &
b110101 '
#1180000
b1010100 "
b1010100 3
b11 4
b111 5
b110110 $
b110110 /
b110110 &
b110110 '
#1190000
b1010101 "
b1010101 3
b11 4
b111 5
b110111 $
b110111 /
b110111 &
b110111 '
#1200000
b1010110 "
b1010110 3
b11 4
b111 5
b111000 $
b111000 /
b111000 &
b111000 '
#1210000
b1010111 "
b1010111 3
b11 4
b111 5
b111001 $
b111001 /
b111001 &
b111001 '
#1220000
b1011000 "
b1011000 3
b11 4
b111 5
b111010 $
b111010 /
b111010 &
b111010 '
#1230000
b1011001 "
b1011001 3
b11 4
b111 5
b111011 $
b111011 /
b111011 &
b111011 '
#1240000
b1100000 "
b1100000 3
b11 4
b111 5
b111100 $
b111100 /
b111100 &
b111100 '
#1250000
b1100001 "
b1100001 3
b11 4
b111 5
b111101 $
b111101 /
b111101 &
b111101 '
#1260000
b1100010 "
b1100010 3
b11 4
b111 5
b111110 $
b111110 /
b111110 &
b111110 '
#1270000
b1100011 "
b1100011 3
b11 4
b111 5
b111111 $
b111111 /
b111111 &
b111111 '
#1280000
b1100100 "
b1100100 3
b11 4
b111 5
b1000000 $
b1000000 /
b1000000 &
b1000000 '
#1290000
b1100101 "
b1100101 3
b11 4
b111 5
b1000001 $
b1000001 /
b1000001 &
b1000001 '
#1300000
b1100110 "
b1100110 3
b11 4
b111 5
b1000010 $
b1000010 /
b1000010 &
b1000010 '
#1310000
b1100111 "
b1100111 3
b11 4
b111 5
b1000011 $
b1000011 /
b1000011 &
b1000011 '
#1320000
b1101000 "
b1101000 3
b11 4
b111 5
b1000100 $
b1000100 /
b1000100 &
b1000100 '
#1330000
b1101001 "
b1101001 3
b11 4
b111 5
b1000101 $
b1000101 /
b1000101 &
b1000101 '
#1340000
b1110000 "
b1110000 3
b11 4
b111 5
b1000110 $
b1000110 /
b1000110 &
b1000110 '
#1350000
b1110001 "
b1110001 3
b11 4
b111 5
b1000111 $
b1000111 /
b1000111 &
b1000111 '
#1360000
b1110010 "
b1110010 3
b11 4
b111 5
b1001000 $
b1001000 /
b1001000 &
b1001000 '
#1370000
b1110011 "
b1110011 3
b11 4
b111 5
b1001001 $
b1001001 /
b1001001 &
b1001001 '
#1380000
b1110100 "
b1110100 3
b11 4
b111 5
b1001010 $
b1001010 /
b1001010 &
b1001010 '
#1390000
b1110101 "
b1110101 3
b11 4
b111 5
b1001011 $
b1001011 /
b1001011 &
b1001011 '
#1400000
b1110110 "
b1110110 3
b11 4
b111 5
b1001100 $
b1001100 /
b1001100 &
b1001100 '
#1410000
b1110111 "
b1110111 3
b11 4
b111 5
b1001101 $
b1001101 /
b1001101 &
b1001101 '
#1420000
b1111000 "
b1111000 3
b11 4
b111 5
b1001110 $
b1001110 /
b1001110 &
b1001110 '
#1430000
b1111001 "
b1111001 3
b11 4
b111 5
b1001111 $
b1001111 /
b1001111 &
b1001111 '
#1440000
b10000000 "
b10000000 3
b11 4
b111 5
b1010000 $
b1010000 /
b1010000 &
b1010000 '
#1450000
b10000001 "
b10000001 3
b11 4
b111 5
b1010001 $
b1010001 /
b1010001 &
b1010001 '
#1460000
b10000010 "
b10000010 3
b11 4
b111 5
b1010010 $
b1010010 /
b1010010 &
b1010010 '
#1470000
b10000011 "
b10000011 3
b11 4
b111 5
b1010011 $
b1010011 /
b1010011 &
b1010011 '
#1480000
b10000100 "
b10000100 3
b11 4
b111 5
b1010100 $
b1010100 /
b1010100 &
b1010100 '
#1490000
b10000101 "
b10000101 3
b11 4
b111 5
b1010101 $
b1010101 /
b1010101 &
b1010101 '
#1500000
b10000110 "
b10000110 3
b11 4
b111 5
b1010110 $
b1010110 /
b1010110 &
b1010110 '
#1510000
b10000111 "
b10000111 3
b11 4
b111 5
b1010111 $
b1010111 /
b1010111 &
b1010111 '
#1520000
b10001000 "
b10001000 3
b11 4
b111 5
b1011000 $
b1011000 /
b1011000 &
b1011000 '
#1530000
b10001001 "
b10001001 3
b11 4
b111 5
b1011001 $
b1011001 /
b1011001 &
b1011001 '
#1540000
b10010000 "
b10010000 3
b11 4
b111 5
b1011010 $
b1011010 /
b1011010 &
b1011010 '
#1550000
b10010001 "
b10010001 3
b11 4
b111 5
b1011011 $
b1011011 /
b1011011 &
b1011011 '
#1560000
b10010010 "
b10010010 3
b11 4
b111 5
b1011100 $
b1011100 /
b1011100 &
b1011100 '
#1570000
b10010011 "
b10010011 3
b11 4
b111 5
b1011101 $
b1011101 /
b1011101 &
b1011101 '
#1580000
b10010100 "
b10010100 3
b11 4
b111 5
b1011110 $
b1011110 /
b1011110 &
b1011110 '
#1590000
b10010101 "
b10010101 3
b11 4
b111 5
b1011111 $
b1011111 /
b1011111 &
b1011111 '
#1600000
b10010110 "
b10010110 3
b11 4
b111 5
b1100000 $
b1100000 /
b1100000 &
b1100000 '
#1610000
b10010111 "
b10010111 3
b11 4
b111 5
b1100001 $
b1100001 /
b1100001 &
b1100001 '
#1620000
b10011000 "
b10011000 3
b11 4
b111 5
b1100010 $
b1100010 /
b1100010 &
b1100010 '
#1630000
b10011001 "
b10011001 3
b11 4
b111 5
b1100011 $
b1100011 /
b1100011 &
b1100011 '
#1640000
b100000000 "
b100000000 3
b11 4
b111 5
b1100100 $
b1100100 /
b1100100 &
b1100100 '
#1650000
b100000001 "
b100000001 3
b11 4
b111 5
b1100101 $
b1100101 /
b1100101 &
b1100101 '
#1660000
b100000010 "
b100000010 3
b11 4
b111 5
b1100110 $
b1100110 /
b1100110 &
b1100110 '
#1670000
b100000011 "
b100000011 3
b11 4
b111 5
b1100111 $
b1100111 /
b1100111 &
b1100111 '
#1680000
b100000100 "
b100000100 3
b11 4
b111 5
b1101000 $
b1101000 /
b1101000 &
b1101000 '
#1690000
b100000101 "
b100000101 3
b11 4
b111 5
b1101001 $
b1101001 /
b1101001 &
b1101001 '
#1700000
b100000110 "
b100000110 3
b11 4
b111 5
b1101010 $
b1101010 /
b1101010 &
b1101010 '
#1710000
b100000111 "
b100000111 3
b11 4
b111 5
b1101011 $
b1101011 /
b1101011 &
b1101011 '
#1720000
b100001000 "
b100001000 3
b11 4
b111 5
b1101100 $
b1101100 /
b1101100 &
b1101100 '
#1730000
b100001001 "
b100001001 3
b11 4
b111 5
b1101101 $
b1101101 /
b1101101 &
b1101101 '
#1740000
b100010000 "
b100010000 3
b11 4
b111 5
b1101110 $
b1101110 /
b1101110 &
b1101110 '
#1750000
b100010001 "
b100010001 3
b11 4
b111 5
b1101111 $
b1101111 /
b1101111 &
b1101111 '
#1760000
b100010010 "
b100010010 3
b11 4
b111 5
b1110000 $
b1110000 /
b1110000 &
b1110000 '
#1770000
b100010011 "
b100010011 3
b11 4
b111 5
b1110001 $
b1110001 /
b1110001 &
b1110001 '
#1780000
b100010100 "
b100010100 3
b11 4
b111 5
b1110010 $
b1110010 /
b1110010 &
b1110010 '
#1790000
b100010101 "
b100010101 3
b11 4
b111 5
b1110011 $
b1110011 /
b1110011 &
b1110011 '
#1800000
b100010110 "
b100010110 3
b11 4
b111 5
b1110100 $
b1110100 /
b1110100 &
b1110100 '
#1810000
b100010111 "
b100010111 3
b11 4
b111 5
b1110101 $
b1110101 /
b1110101 &
b1110101 '
#1820000
b100011000 "
b100011000 3
b11 4
b111 5
b1110110 $
b1110110 /
b1110110 &
b1110110 '
#1830000
b100011001 "
b100011001 3
b11 4
b111 5
b1110111 $
b1110111 /
b1110111 &
b1110111 '
#1840000
b100100000 "
b100100000 3
b11 4
b111 5
b1111000 $
b1111000 /
b1111000 &
b1111000 '
#1850000
b100100001 "
b100100001 3
b11 4
b111 5
b1111001 $
b1111001 /
b1111001 &
b1111001 '
#1860000
b100100010 "
b100100010 3
b11 4
b111 5
b1111010 $
b1111010 /
b1111010 &
b1111010 '
#1870000
b100100011 "
b100100011 3
b11 4
b111 5
b1111011 $
b1111011 /
b1111011 &
b1111011 '
#1880000
b100100100 "
b100100100 3
b11 4
b111 5
b1111100 $
b1111100 /
b1111100 &
b1111100 '
#1890000
b100100101 "
b100100101 3
b11 4
b111 5
b1111101 $
b1111101 /
b1111101 &
b1111101 '
#1900000
b100100110 "
b100100110 3
b11 4
b111 5
b1111110 $
b1111110 /
b1111110 &
b1111110 '
#1910000
b100100111 "
b100100111 3
b11 4
b111 5
b1111111 $
b1111111 /
b1111111 &
b1111111 '
#1920000
b10000000 &
b10000000 '
